scenegraph/__init__.py
scenegraph/algo.py
scenegraph/io.py
scenegraph/scene.py
scenegraph/shape.py
scenegraph/transfo.py
scenegraph/triangle.py
scenegraph/triangle_set.py
scenegraph/version.py
scenegraph/topo/__init__.py
scenegraph/topo/graph.py
scenegraph/topo/id_dict.py
scenegraph/topo/id_generator.py
scenegraph-1.1.1.dist-info/licenses/AUTHORS.rst
scenegraph-1.1.1.dist-info/licenses/LICENSE
scenegraph-1.1.1.dist-info/METADATA
scenegraph-1.1.1.dist-info/WHEEL
scenegraph-1.1.1.dist-info/top_level.txt
scenegraph-1.1.1.dist-info/RECORD
